[{"ScoreID": "CC2020.035b",
        "PerformedBy": "Cantāmus AI Ensemble",
        "LastModified": "20240323", "BaseFileName": "035b - O LORD, I Love You, God, My Strength - Psalm 18", "Composer": "Music: Heinrich Schütz, 1628  ", "Text": "Text: Douglas Wilson, 2001 ©", "ScoreName": "ICH LIEB DICH, HERR [BECKER 18]", "Meter": "8 7. 8 7. 5 5. 5 6. 7.", "Verse1": "0", "Verse2": "30", "Verse3": "59", "Verse4": "88", "Verse5": "nil", "Verse6": "nil", "Verse7": "nil", "Verse8": "nil", "Verse9": "nil", "Verse10": "nil"}]