[{"ScoreID": "CC2020.634",
        "PerformedBy": "Cantāmus AI Ensemble",
        "LastModified": "20241230", "BaseFileName": "634 - Come, Ye Faithful, Raise the Strain", "Composer": "Music: Bohemian Brethren’s Gesangbuch, 1544 ", "Text": "Text: John of Damascus, c. 700s; tr. John Mason Neale, 1859 ", "ScoreName": "AVE VIRGO VIRGINUM ", "Meter": "7 6. 7 6. 7 6. 7 6. Trochaic", "Verse1": "0", "Verse2": "31", "Verse3": "61", "Verse4": "91", "Verse5": "121", "Verse6": "nil", "Verse7": "nil", "Verse8": "nil", "Verse9": "nil", "Verse10": "nil"}]